lib/__init__.py
lib/x1.py
lib/x2.py
lib/x3.py
lib/x4.py
lib/x5.py
scripts_lot-1.0.0.dist-info/METADATA
scripts_lot-1.0.0.dist-info/WHEEL
scripts_lot-1.0.0.dist-info/top_level.txt
scripts_lot-1.0.0.dist-info/RECORD
