Metadata-Version: 2.2
Name: scripts_lot
Version: 1.0.0
Summary: A brief description of your library
Home-page: https://github.com/HamzaAhmad6292/lib
Author: tran_nigga
Author-email: your-email@example.com
Classifier: Programming Language :: Python :: 3
Classifier: License :: OSI Approved :: MIT License
Classifier: Operating System :: OS Independent
Dynamic: author
Dynamic: author-email
Dynamic: classifier
Dynamic: description
Dynamic: description-content-type
Dynamic: home-page
Dynamic: summary
